cutted/__init__.py
cutted/__main__.py
cutted/app.py
cutted/core/audio_processor.py
cutted/core/gemini.py
cutted/core/logger.py
cutted/core/transcribe.py
cutted-0.4.4.dist-info/licenses/LICENSE
cutted-0.4.4.dist-info/METADATA
cutted-0.4.4.dist-info/WHEEL
cutted-0.4.4.dist-info/top_level.txt
cutted-0.4.4.dist-info/RECORD
