Metadata-Version: 2.4
Name: cutted
Version: 0.4.4
Summary: AI-powered audio editor controllable via natural language.
Author-email: simon0302010 <simon0302010@gmail.com>
License-Expression: GPL-3.0
Project-URL: Homepage, https://github.com/simon0302010/Cutted
Requires-Python: <3.14,>=3.9
License-File: LICENSE
Requires-Dist: customtkinter
Requires-Dist: matplotlib
Requires-Dist: numpy
Requires-Dist: pydub
Requires-Dist: pygame
Requires-Dist: google-genai
Requires-Dist: python-dotenv
Requires-Dist: audioop-lts; python_version >= "3.13"
Provides-Extra: test
Requires-Dist: pytest; extra == "test"
Provides-Extra: whisper
Requires-Dist: whisper-timestamped; extra == "whisper"
Dynamic: license-file
